{
  "merchant": {
    "BTC": {
      "USD": "61816.72",
      "BTC": "1",
      "EUR": "53162.38",
      "GBP": "45052.87",
      "PLN": "240432.88",
      "CZK": "1345934.73",
      "SEK": "528952.35",
      "NOK": "528952.35",
      "DKK": "406886.42",
      "CHF": "56876.6",
      "ZAR": "881587.25",
      "AUD": "82648.8",
      "JPY": "7052697.96",
      "NZD": "86713.5",
      "TRY": "587724.83",
      "BRL": "330595.22",
      "CAD": "75564.62",
      "CNY": "406886.42",
      "HKD": "480865.77",
      "HUF": "18891155.25",
      "INR": "4599585.63",
      "RUB": "4371507.0",
      "ILS": "195908.28",
      "MYR": "251882.07",
      "MXN": "1253441.58",
      "SGD": "82648.8",
      "RON": "264476.17",
      "IDR": "528952347.0",
      "PHP": "3129895.54",
      "ARS": "6079912.03",
      "THB": "2058180.34",
      "NGN": "25188207.0",
      "PKR": "10579046.94",
      "AED": "229979.28",
      "UAH": "1617591.28",
      "BGN": "103716.15",
      "HRK": "406886.42",
      "RSD": "6222968.79",
      "LTC": "328.9831",
      "ETH": "16.3744",
      "BCH": "100.6107",
      "XRP": "57208.24",
      "CLP": "48086577.0",
      "NANO": "11806.38",
      "TRX": "628931.0",
      "DAI": "62265.3",
      "DOGE": "251889.0",
      "USDT": "62312.96",
      "AVA": "20028.04",
      "BTCV": "8196.72",
      "KRW": "75564621.0",
      "EGP": "1057904.69",
      "SAR": "229979.28",
      "QAR": "220396.81"
    },
    "LTC": {
      "USD": "187.81",
      "BTC": "0.00303967",
      "EUR": "161.52",
      "GBP": "136.88",
      "PLN": "730.48",
      "CZK": "4089.23",
      "SEK": "1607.07",
      "NOK": "1607.07",
      "DKK": "1236.21",
      "CHF": "172.8",
      "ZAR": "2678.45",
      "AUD": "251.1",
      "JPY": "21427.56",
      "NZD": "263.45",
      "TRY": "1785.63",
      "BRL": "1004.42",
      "CAD": "229.58",
      "CNY": "1236.21",
      "HKD": "1460.97",
      "HUF": "57395.25",
      "INR": "13974.5",
      "RUB": "13281.55",
      "ILS": "595.21",
      "MYR": "765.27",
      "MXN": "3808.22",
      "SGD": "251.1",
      "RON": "803.53",
      "IDR": "1607067.0",
      "PHP": "9509.27",
      "ARS": "18472.03",
      "THB": "6253.18",
      "NGN": "76527.0",
      "PKR": "32141.34",
      "AED": "698.72",
      "UAH": "4914.58",
      "BGN": "315.11",
      "HRK": "1236.21",
      "RSD": "18906.67",
      "LTC": "1",
      "ETH": "0.04967",
      "BCH": "0.305823",
      "XRP": "173.8942",
      "CLP": "146097.0",
      "NANO": "35.8875",
      "TRX": "1911.74",
      "DAI": "189.266",
      "DOGE": "765.6599",
      "USDT": "189.4",
      "AVA": "60.8786",
      "BTCV": "24.9153",
      "KRW": "229581.0",
      "EGP": "3214.13",
      "SAR": "698.72",
      "QAR": "669.61"
    },
    "ETH": {
      "USD": "3774.6",
      "BTC": "0.061071",
      "EUR": "3246.16",
      "GBP": "2750.98",
      "PLN": "14681.11",
      "CZK": "82184.36",
      "SEK": "32298.45",
      "NOK": "32298.45",
      "DKK": "24844.96",
      "CHF": "3472.95",
      "ZAR": "53830.76",
      "AUD": "5046.63",
      "JPY": "430646.04",
      "NZD": "5294.83",
      "TRY": "35887.17",
      "BRL": "20186.53",
      "CAD": "4614.06",
      "CNY": "24844.96",
      "HKD": "29362.23",
      "HUF": "1153516.18",
      "INR": "280856.11",
      "RUB": "266929.36",
      "ILS": "11962.39",
      "MYR": "15380.22",
      "MXN": "76536.62",
      "SGD": "5046.63",
      "RON": "16149.23",
      "IDR": "32298453.0",
      "PHP": "191115.11",
      "ARS": "371246.59",
      "THB": "125674.91",
      "NGN": "1538021.57",
      "PKR": "645969.06",
      "AED": "14042.81",
      "UAH": "98772.03",
      "BGN": "6333.03",
      "HRK": "24844.96",
      "RSD": "379981.8",
      "LTC": "20.1329",
      "ETH": "1",
      "BCH": "6.144396",
      "XRP": "3493.76",
      "CLP": "2936223.0",
      "NANO": "721.5007",
      "TRX": "38409.43",
      "DAI": "3806.88",
      "DOGE": "15383.12",
      "USDT": "3805.86",
      "AVA": "1223.13",
      "BTCV": "500.582",
      "KRW": "4614064.71",
      "EGP": "64596.91",
      "SAR": "14042.81",
      "QAR": "13457.69"
    },
    "BCH": {
      "USD": "614.24",
      "BTC": "0.0099393",
      "EUR": "528.25",
      "GBP": "447.67",
      "PLN": "2389.05",
      "CZK": "13373.82",
      "SEK": "5255.91",
      "NOK": "5255.91",
      "DKK": "4043.01",
      "CHF": "565.15",
      "ZAR": "8759.85",
      "AUD": "821.24",
      "JPY": "70078.8",
      "NZD": "861.62",
      "TRY": "5839.9",
      "BRL": "3284.94",
      "CAD": "750.84",
      "CNY": "4043.01",
      "HKD": "4778.1",
      "HUF": "187711.07",
      "INR": "45703.57",
      "RUB": "43437.27",
      "ILS": "1946.63",
      "MYR": "2502.81",
      "MXN": "12454.76",
      "SGD": "821.24",
      "RON": "2627.96",
      "IDR": "5255910.0",
      "PHP": "31100.06",
      "ARS": "60412.76",
      "THB": "20451.01",
      "NGN": "250281.43",
      "PKR": "105118.2",
      "AED": "2285.18",
      "UAH": "16073.12",
      "BGN": "1030.57",
      "HRK": "4043.01",
      "RSD": "61834.24",
      "LTC": "3.269862",
      "ETH": "0.16275",
      "BCH": "1",
      "XRP": "568.6098",
      "CLP": "477810.0",
      "NANO": "117.3471",
      "TRX": "6251.13",
      "DAI": "618.8735",
      "DOGE": "2503.6",
      "USDT": "619.7",
      "AVA": "199.0647",
      "BTCV": "81.4697",
      "KRW": "750844.29",
      "EGP": "10511.82",
      "SAR": "2285.18",
      "QAR": "2189.96"
    },
    "XRP": {
      "USD": "1.0804",
      "BTC": "0.00001748",
      "EUR": "0.9292",
      "GBP": "0.7874",
      "PLN": "4.2023",
      "CZK": "23.5245",
      "SEK": "9.2451",
      "NOK": "9.2451",
      "DKK": "7.1116",
      "CHF": "0.9941",
      "ZAR": "15.4085",
      "AUD": "1.4445",
      "JPY": "123.2682",
      "NZD": "1.5156",
      "TRY": "10.2723",
      "BRL": "5.7782",
      "CAD": "1.3207",
      "CNY": "7.1116",
      "HKD": "8.4047",
      "HUF": "330.1827",
      "INR": "80.3923",
      "RUB": "76.4059",
      "ILS": "3.4241",
      "MYR": "4.4024",
      "MXN": "21.9079",
      "SGD": "1.4445",
      "RON": "4.6226",
      "IDR": "9245.115",
      "PHP": "54.7048",
      "ARS": "106.2657",
      "THB": "35.9732",
      "NGN": "440.2436",
      "PKR": "184.9023",
      "AED": "4.0196",
      "UAH": "28.2725",
      "BGN": "1.8128",
      "HRK": "7.1116",
      "RSD": "108.7661",
      "LTC": "0.00575062",
      "ETH": "0.00028622",
      "BCH": "0.00175868",
      "XRP": "1",
      "CLP": "840.465",
      "NANO": "0.206375",
      "TRX": "10.9937",
      "DAI": "1.088397",
      "DOGE": "4.403023",
      "USDT": "1.0893",
      "AVA": "0.35009",
      "BTCV": "0.143279",
      "KRW": "1320.7307",
      "EGP": "18.4902",
      "SAR": "4.0196",
      "QAR": "3.8521"
    },
    "NANO": {
      "USD": "5.24",
      "BTC": "0.0000847",
      "EUR": "4.5",
      "GBP": "3.82",
      "PLN": "20.37",
      "CZK": "114.02",
      "SEK": "44.81",
      "NOK": "44.81",
      "DKK": "34.47",
      "CHF": "4.82",
      "ZAR": "74.68",
      "AUD": "7.0",
      "JPY": "597.47",
      "NZD": "7.35",
      "TRY": "49.79",
      "BRL": "28.01",
      "CAD": "6.4",
      "CNY": "34.47",
      "HKD": "40.74",
      "HUF": "1600.35",
      "INR": "389.65",
      "RUB": "370.33",
      "ILS": "16.6",
      "MYR": "21.34",
      "MXN": "106.18",
      "SGD": "7.0",
      "RON": "22.4",
      "IDR": "44809.88",
      "PHP": "265.15",
      "ARS": "515.06",
      "THB": "174.36",
      "NGN": "2133.8",
      "PKR": "896.2",
      "AED": "19.48",
      "UAH": "137.03",
      "BGN": "8.79",
      "HRK": "34.47",
      "RSD": "527.18",
      "LTC": "0.02786487",
      "ETH": "0.00138691",
      "BCH": "0.00852173",
      "XRP": "4.845538",
      "CLP": "4073.63",
      "NANO": "1",
      "TRX": "53.2704",
      "DAI": "5.273871",
      "DOGE": "21.335",
      "USDT": "5.279",
      "AVA": "1.696375",
      "BTCV": "0.694262",
      "KRW": "6401.41",
      "EGP": "89.62",
      "SAR": "19.48",
      "QAR": "18.67"
    },
    "TRX": {
      "USD": "0.0979",
      "BTC": "0.00000159",
      "EUR": "0.0842",
      "GBP": "0.0713",
      "PLN": "0.3807",
      "CZK": "2.1313",
      "SEK": "0.8376",
      "NOK": "0.8376",
      "DKK": "0.6443",
      "CHF": "0.0901",
      "ZAR": "1.396",
      "AUD": "0.1309",
      "JPY": "11.1679",
      "NZD": "0.1373",
      "TRY": "0.9307",
      "BRL": "0.5235",
      "CAD": "0.1197",
      "CNY": "0.6443",
      "HKD": "0.7614",
      "HUF": "29.9139",
      "INR": "7.2834",
      "RUB": "6.9222",
      "ILS": "0.3102",
      "MYR": "0.3989",
      "MXN": "1.9848",
      "SGD": "0.1309",
      "RON": "0.4188",
      "IDR": "837.5895",
      "PHP": "4.9562",
      "ARS": "9.6275",
      "THB": "3.2591",
      "NGN": "39.8852",
      "PKR": "16.7518",
      "AED": "0.3642",
      "UAH": "2.5614",
      "BGN": "0.1642",
      "HRK": "0.6443",
      "RSD": "9.854",
      "LTC": "0.00052308",
      "ETH": "0.00002604",
      "BCH": "0.00015997",
      "XRP": "0.0909611",
      "CLP": "76.1445",
      "NANO": "0.01877214",
      "TRX": "1",
      "DAI": "0.09900183",
      "DOGE": "0.400504",
      "USDT": "0.09868",
      "AVA": "0.03184458",
      "BTCV": "0.01303279",
      "KRW": "119.6556",
      "EGP": "1.6752",
      "SAR": "0.3642",
      "QAR": "0.349"
    },
    "DAI": {
      "USD": "0.9921",
      "BTC": "0.00001606",
      "EUR": "0.8532",
      "GBP": "0.723",
      "PLN": "3.8586",
      "CZK": "21.6001",
      "SEK": "8.4889",
      "NOK": "8.4889",
      "DKK": "6.5299",
      "CHF": "0.9128",
      "ZAR": "14.1481",
      "AUD": "1.3264",
      "JPY": "113.1847",
      "NZD": "1.3916",
      "TRY": "9.4321",
      "BRL": "5.3055",
      "CAD": "1.2127",
      "CNY": "6.5299",
      "HKD": "7.7171",
      "HUF": "303.1734",
      "INR": "73.8161",
      "RUB": "70.1558",
      "ILS": "3.144",
      "MYR": "4.0423",
      "MXN": "20.1158",
      "SGD": "1.3264",
      "RON": "4.2444",
      "IDR": "8488.854",
      "PHP": "50.2299",
      "ARS": "97.573",
      "THB": "33.0306",
      "NGN": "404.2311",
      "PKR": "169.7771",
      "AED": "3.6908",
      "UAH": "25.9598",
      "BGN": "1.6645",
      "HRK": "6.5299",
      "RSD": "99.8689",
      "LTC": "0.00528357",
      "ETH": "0.00026268",
      "BCH": "0.00161584",
      "XRP": "0.918782",
      "CLP": "771.714",
      "NANO": "0.189614",
      "TRX": "10.1008",
      "DAI": "1",
      "DOGE": "4.045418",
      "USDT": "0.9998",
      "AVA": "0.321657",
      "BTCV": "0.131642",
      "KRW": "1212.6934",
      "EGP": "16.9777",
      "SAR": "3.6908",
      "QAR": "3.537"
    },
    "DOGE": {
      "USD": "0.2454",
      "BTC": "0.00000397",
      "EUR": "0.211",
      "GBP": "0.1788",
      "PLN": "0.9544",
      "CZK": "5.3424",
      "SEK": "2.0996",
      "NOK": "2.0996",
      "DKK": "1.6151",
      "CHF": "0.2258",
      "ZAR": "3.4993",
      "AUD": "0.3281",
      "JPY": "27.9943",
      "NZD": "0.3442",
      "TRY": "2.3329",
      "BRL": "1.3122",
      "CAD": "0.2999",
      "CNY": "1.6151",
      "HKD": "1.9087",
      "HUF": "74.9848",
      "INR": "18.2572",
      "RUB": "17.3519",
      "ILS": "0.7776",
      "MYR": "0.9998",
      "MXN": "4.9753",
      "SGD": "0.3281",
      "RON": "1.0498",
      "IDR": "2099.5742",
      "PHP": "12.4235",
      "ARS": "24.133",
      "THB": "8.1695",
      "NGN": "99.9797",
      "PKR": "41.9915",
      "AED": "0.9129",
      "UAH": "6.4207",
      "BGN": "0.4117",
      "HRK": "1.6151",
      "RSD": "24.7009",
      "LTC": "0.00130606",
      "ETH": "0.00006501",
      "BCH": "0.00039942",
      "XRP": "0.227117",
      "CLP": "190.8704",
      "NANO": "0.04687131",
      "TRX": "2.496855",
      "DAI": "0.247193",
      "DOGE": "1",
      "USDT": "0.2472",
      "AVA": "0.07951132",
      "BTCV": "0.03254098",
      "KRW": "299.9392",
      "EGP": "4.1991",
      "SAR": "0.9129",
      "QAR": "0.8748"
    },
    "USDT": {
      "USD": "0.9923",
      "BTC": "0.00001605",
      "EUR": "0.8534",
      "GBP": "0.7232",
      "PLN": "3.8596",
      "CZK": "21.6062",
      "SEK": "8.4912",
      "NOK": "8.4912",
      "DKK": "6.5317",
      "CHF": "0.913",
      "ZAR": "14.1521",
      "AUD": "1.3268",
      "JPY": "113.2164",
      "NZD": "1.392",
      "TRY": "9.4347",
      "BRL": "5.307",
      "CAD": "1.213",
      "CNY": "6.5317",
      "HKD": "7.7193",
      "HUF": "303.2582",
      "INR": "73.8368",
      "RUB": "70.1755",
      "ILS": "3.1449",
      "MYR": "4.0434",
      "MXN": "20.1214",
      "SGD": "1.3268",
      "RON": "4.2456",
      "IDR": "8491.23",
      "PHP": "50.244",
      "ARS": "97.6003",
      "THB": "33.0398",
      "NGN": "404.3443",
      "PKR": "169.8246",
      "AED": "3.6918",
      "UAH": "25.9671",
      "BGN": "1.6649",
      "HRK": "6.5317",
      "RSD": "99.8968",
      "LTC": "0.00527983",
      "ETH": "0.00026275",
      "BCH": "0.00161368",
      "XRP": "0.918021",
      "CLP": "771.93",
      "NANO": "0.18943",
      "TRX": "10.1338",
      "DAI": "1.0002",
      "DOGE": "4.045307",
      "USDT": "1",
      "AVA": "0.32141",
      "BTCV": "0.131541",
      "KRW": "1213.0329",
      "EGP": "16.9825",
      "SAR": "3.6918",
      "QAR": "3.538"
    },
    "BTT": {
      "USD": "0.003551",
      "BTC": "0.00000006",
      "EUR": "0.003054",
      "GBP": "0.002588",
      "PLN": "0.01381",
      "CZK": "0.077311",
      "SEK": "0.030383",
      "NOK": "0.030383",
      "DKK": "0.023372",
      "CHF": "0.003267",
      "ZAR": "0.050639",
      "AUD": "0.004747",
      "JPY": "0.405108",
      "NZD": "0.004981",
      "TRY": "0.033759",
      "BRL": "0.018989",
      "CAD": "0.00434",
      "CNY": "0.023372",
      "HKD": "0.027621",
      "HUF": "1.085111",
      "INR": "0.264201",
      "RUB": "0.2511",
      "ILS": "0.011253",
      "MYR": "0.014468",
      "MXN": "0.071998",
      "SGD": "0.004747",
      "RON": "0.015192",
      "IDR": "30.3831",
      "PHP": "0.179782",
      "ARS": "0.349231",
      "THB": "0.118222",
      "NGN": "1.446814",
      "PKR": "0.607662",
      "AED": "0.01321",
      "UAH": "0.092915",
      "BGN": "0.005957",
      "HRK": "0.023372",
      "RSD": "0.357448",
      "LTC": "0.00001974",
      "ETH": "0.00000098",
      "BCH": "0.00000604",
      "XRP": "0.00343249",
      "CLP": "2.7621",
      "NANO": "0.00070838",
      "TRX": "0.03773585",
      "DAI": "0.00373592",
      "DOGE": "0.01511335",
      "USDT": "0.00373878",
      "AVA": "0.00120168",
      "BTCV": "0.0004918",
      "KRW": "4.340443",
      "EGP": "0.060766",
      "SAR": "0.01321",
      "QAR": "0.01266"
    },
    "AVA": {
      "USD": "3.11",
      "BTC": "0.00004993",
      "EUR": "2.67",
      "GBP": "2.22",
      "PLN": "12.23",
      "CZK": "67.93",
      "SEK": "26.78",
      "NOK": "26.0",
      "DKK": "19.84",
      "CHF": "2.86",
      "ZAR": "45.36",
      "AUD": "4.16",
      "JPY": "354.5",
      "NZD": "4.35",
      "TRY": "29.01",
      "BRL": "17.12",
      "CAD": "3.83",
      "CNY": "19.9",
      "HKD": "24.16",
      "HUF": "963.75",
      "INR": "232.76",
      "RUB": "220.75",
      "ILS": "9.98",
      "MYR": "12.96",
      "MXN": "63.21",
      "SGD": "4.18",
      "RON": "13.2",
      "IDR": "43719.96",
      "PHP": "157.43",
      "ARS": "308.27",
      "THB": "103.57",
      "NGN": "1281.53",
      "PKR": "534.28",
      "AED": "11.41",
      "UAH": "81.5",
      "BGN": "5.22",
      "HRK": "20.02",
      "RSD": "314.17",
      "LTC": "0.01642613",
      "ETH": "0.00081757",
      "BCH": "0.00502349",
      "XRP": "2.856407",
      "CLP": "2538.49",
      "NANO": "0.589492",
      "TRX": "31.4025",
      "DAI": "3.108906",
      "DOGE": "12.5768",
      "USDT": "3.111286",
      "AVA": "1",
      "BTCV": "0.409262",
      "KRW": "3665.16",
      "EGP": "48.76",
      "SAR": "11.65",
      "QAR": "11.31"
    },
    "BTCV": {
      "USD": "7.59",
      "BTC": "0.000122",
      "EUR": "6.51",
      "GBP": "5.43",
      "PLN": "29.88",
      "CZK": "165.97",
      "SEK": "65.42",
      "NOK": "63.51",
      "DKK": "48.48",
      "CHF": "6.99",
      "ZAR": "110.82",
      "AUD": "10.17",
      "JPY": "866.1",
      "NZD": "10.64",
      "TRY": "70.89",
      "BRL": "41.83",
      "CAD": "9.36",
      "CNY": "48.61",
      "HKD": "59.04",
      "HUF": "2354.6",
      "INR": "568.67",
      "RUB": "539.32",
      "ILS": "24.39",
      "MYR": "31.66",
      "MXN": "154.43",
      "SGD": "10.21",
      "RON": "32.24",
      "IDR": "106814.97",
      "PHP": "384.62",
      "ARS": "753.15",
      "THB": "253.05",
      "NGN": "3130.99",
      "PKR": "1305.33",
      "AED": "27.88",
      "UAH": "199.13",
      "BGN": "12.74",
      "HRK": "48.92",
      "RSD": "767.58",
      "LTC": "0.04013158",
      "ETH": "0.00199673",
      "BCH": "0.01227451",
      "XRP": "6.95553",
      "CLP": "6201.94",
      "NANO": "1.440378",
      "TRX": "76.7296",
      "DAI": "7.596367",
      "DOGE": "30.7305",
      "USDT": "7.599713",
      "AVA": "2.443421",
      "BTCV": "1",
      "KRW": "8954.57",
      "EGP": "119.14",
      "SAR": "28.47",
      "QAR": "27.63"
    },
    "USD": {
      "USD": "1.0",
      "EUR": "0.86",
      "GBP": "0.73",
      "PLN": "3.94",
      "CZK": "21.87",
      "SEK": "8.62",
      "NOK": "8.37",
      "DKK": "6.39",
      "CHF": "0.92",
      "ZAR": "14.6",
      "AUD": "1.34",
      "JPY": "114.11",
      "NZD": "1.4",
      "TRY": "9.34",
      "BRL": "5.51",
      "CAD": "1.23",
      "CNY": "6.41",
      "HKD": "7.78",
      "HUF": "310.23",
      "INR": "74.92",
      "RUB": "71.06",
      "ILS": "3.21",
      "MYR": "4.17",
      "MXN": "20.35",
      "SGD": "1.35",
      "RON": "4.25",
      "IDR": "14073.3",
      "PHP": "50.68",
      "ARS": "99.23",
      "THB": "33.34",
      "NGN": "412.52",
      "PKR": "171.98",
      "AED": "3.67",
      "UAH": "26.24",
      "BGN": "1.68",
      "HRK": "6.44",
      "RSD": "101.13",
      "CLP": "817.13",
      "KRW": "1179.8",
      "EGP": "15.7",
      "SAR": "3.75",
      "QAR": "3.64"
    },
    "EUR": {
      "USD": "1.16",
      "EUR": "1.0",
      "GBP": "0.85",
      "PLN": "4.59",
      "CZK": "25.47",
      "SEK": "10.04",
      "NOK": "9.75",
      "DKK": "7.44",
      "CHF": "1.07",
      "ZAR": "17.01",
      "AUD": "1.56",
      "JPY": "132.94",
      "NZD": "1.63",
      "TRY": "10.88",
      "BRL": "6.42",
      "CAD": "1.44",
      "CNY": "7.46",
      "HKD": "9.06",
      "HUF": "361.41",
      "INR": "87.29",
      "RUB": "82.78",
      "ILS": "3.74",
      "MYR": "4.86",
      "MXN": "23.7",
      "SGD": "1.57",
      "RON": "4.95",
      "IDR": "16395.39",
      "PHP": "59.04",
      "ARS": "115.6",
      "THB": "38.84",
      "NGN": "480.59",
      "PKR": "200.36",
      "AED": "4.28",
      "UAH": "30.56",
      "BGN": "1.96",
      "HRK": "7.51",
      "RSD": "117.82",
      "CLP": "951.96",
      "KRW": "1374.47",
      "EGP": "18.29",
      "SAR": "4.37",
      "QAR": "4.24"
    },
    "GBP": {
      "USD": "1.38",
      "EUR": "1.18",
      "GBP": "1.0",
      "PLN": "5.42",
      "CZK": "30.12",
      "SEK": "11.87",
      "NOK": "11.53",
      "DKK": "8.8",
      "CHF": "1.27",
      "ZAR": "20.11",
      "AUD": "1.85",
      "JPY": "157.18",
      "NZD": "1.93",
      "TRY": "12.86",
      "BRL": "7.59",
      "CAD": "1.7",
      "CNY": "8.82",
      "HKD": "10.71",
      "HUF": "427.32",
      "INR": "103.2",
      "RUB": "97.88",
      "ILS": "4.43",
      "MYR": "5.75",
      "MXN": "28.03",
      "SGD": "1.85",
      "RON": "5.85",
      "IDR": "19385.06",
      "PHP": "69.8",
      "ARS": "136.68",
      "THB": "45.92",
      "NGN": "568.22",
      "PKR": "236.9",
      "AED": "5.06",
      "UAH": "36.14",
      "BGN": "2.31",
      "HRK": "8.88",
      "RSD": "139.3",
      "CLP": "1125.54",
      "KRW": "1625.1",
      "EGP": "21.62",
      "SAR": "5.17",
      "QAR": "5.02"
    },
    "PLN": {
      "USD": "0.25",
      "EUR": "0.22",
      "GBP": "0.18",
      "PLN": "1.0",
      "CZK": "5.55",
      "SEK": "2.19",
      "NOK": "2.13",
      "DKK": "1.62",
      "CHF": "0.23",
      "ZAR": "3.71",
      "AUD": "0.34",
      "JPY": "28.99",
      "NZD": "0.36",
      "TRY": "2.37",
      "BRL": "1.4",
      "CAD": "0.31",
      "CNY": "1.63",
      "HKD": "1.98",
      "HUF": "78.8",
      "INR": "19.03",
      "RUB": "18.05",
      "ILS": "0.82",
      "MYR": "1.06",
      "MXN": "5.17",
      "SGD": "0.34",
      "RON": "1.08",
      "IDR": "3574.92",
      "PHP": "12.87",
      "ARS": "25.21",
      "THB": "8.47",
      "NGN": "104.79",
      "PKR": "43.69",
      "AED": "0.93",
      "UAH": "6.66",
      "BGN": "0.43",
      "HRK": "1.64",
      "RSD": "25.69",
      "CLP": "207.57",
      "KRW": "299.69",
      "EGP": "3.99",
      "SAR": "0.95",
      "QAR": "0.92"
    },
    "CZK": {
      "USD": "0.0457",
      "EUR": "0.0393",
      "GBP": "0.0332",
      "PLN": "0.18",
      "CZK": "1.0",
      "SEK": "0.39",
      "NOK": "0.38",
      "DKK": "0.29",
      "CHF": "0.0421",
      "ZAR": "0.67",
      "AUD": "0.06",
      "JPY": "5.22",
      "NZD": "0.06",
      "TRY": "0.43",
      "BRL": "0.25",
      "CAD": "0.06",
      "CNY": "0.29",
      "HKD": "0.36",
      "HUF": "14.19",
      "INR": "3.43",
      "RUB": "3.25",
      "ILS": "0.15",
      "MYR": "0.19",
      "MXN": "0.93",
      "SGD": "0.06",
      "RON": "0.19",
      "IDR": "643.59",
      "PHP": "2.32",
      "ARS": "4.54",
      "THB": "1.52",
      "NGN": "18.87",
      "PKR": "7.87",
      "AED": "0.17",
      "UAH": "1.2",
      "BGN": "0.08",
      "HRK": "0.29",
      "RSD": "4.62",
      "CLP": "37.37",
      "KRW": "53.95",
      "EGP": "0.72",
      "SAR": "0.17",
      "QAR": "0.17"
    },
    "SEK": {
      "USD": "0.12",
      "EUR": "0.1",
      "GBP": "0.08",
      "PLN": "0.46",
      "CZK": "2.54",
      "SEK": "1.0",
      "NOK": "0.97",
      "DKK": "0.74",
      "CHF": "0.11",
      "ZAR": "1.69",
      "AUD": "0.16",
      "JPY": "13.24",
      "NZD": "0.16",
      "TRY": "1.08",
      "BRL": "0.64",
      "CAD": "0.14",
      "CNY": "0.74",
      "HKD": "0.9",
      "HUF": "35.99",
      "INR": "8.69",
      "RUB": "8.24",
      "ILS": "0.37",
      "MYR": "0.48",
      "MXN": "2.36",
      "SGD": "0.16",
      "RON": "0.49",
      "IDR": "1632.65",
      "PHP": "5.88",
      "ARS": "11.51",
      "THB": "3.87",
      "NGN": "47.86",
      "PKR": "19.95",
      "AED": "0.43",
      "UAH": "3.04",
      "BGN": "0.19",
      "HRK": "0.75",
      "RSD": "11.73",
      "CLP": "94.8",
      "KRW": "136.87",
      "EGP": "1.82",
      "SAR": "0.44",
      "QAR": "0.42"
    },
    "NOK": {
      "USD": "0.12",
      "EUR": "0.1",
      "GBP": "0.09",
      "PLN": "0.47",
      "CZK": "2.61",
      "SEK": "1.03",
      "NOK": "1.0",
      "DKK": "0.76",
      "CHF": "0.11",
      "ZAR": "1.74",
      "AUD": "0.16",
      "JPY": "13.64",
      "NZD": "0.17",
      "TRY": "1.12",
      "BRL": "0.66",
      "CAD": "0.15",
      "CNY": "0.77",
      "HKD": "0.93",
      "HUF": "37.07",
      "INR": "8.95",
      "RUB": "8.49",
      "ILS": "0.38",
      "MYR": "0.5",
      "MXN": "2.43",
      "SGD": "0.16",
      "RON": "0.51",
      "IDR": "1681.75",
      "PHP": "6.06",
      "ARS": "11.86",
      "THB": "3.98",
      "NGN": "49.3",
      "PKR": "20.55",
      "AED": "0.44",
      "UAH": "3.14",
      "BGN": "0.2",
      "HRK": "0.77",
      "RSD": "12.09",
      "CLP": "97.65",
      "KRW": "140.99",
      "EGP": "1.88",
      "SAR": "0.45",
      "QAR": "0.44"
    },
    "DKK": {
      "USD": "0.16",
      "EUR": "0.13",
      "GBP": "0.11",
      "PLN": "0.62",
      "CZK": "3.42",
      "SEK": "1.35",
      "NOK": "1.31",
      "DKK": "1.0",
      "CHF": "0.14",
      "ZAR": "2.29",
      "AUD": "0.21",
      "JPY": "17.87",
      "NZD": "0.22",
      "TRY": "1.46",
      "BRL": "0.86",
      "CAD": "0.19",
      "CNY": "1.0",
      "HKD": "1.22",
      "HUF": "48.57",
      "INR": "11.73",
      "RUB": "11.13",
      "ILS": "0.5",
      "MYR": "0.65",
      "MXN": "3.19",
      "SGD": "0.21",
      "RON": "0.67",
      "IDR": "2203.5",
      "PHP": "7.93",
      "ARS": "15.54",
      "THB": "5.22",
      "NGN": "64.59",
      "PKR": "26.93",
      "AED": "0.58",
      "UAH": "4.11",
      "BGN": "0.26",
      "HRK": "1.01",
      "RSD": "15.83",
      "CLP": "127.94",
      "KRW": "184.73",
      "EGP": "2.46",
      "SAR": "0.59",
      "QAR": "0.57"
    },
    "CHF": {
      "USD": "1.09",
      "EUR": "0.93",
      "GBP": "0.79",
      "PLN": "4.28",
      "CZK": "23.75",
      "SEK": "9.36",
      "NOK": "9.09",
      "DKK": "6.94",
      "CHF": "1.0",
      "ZAR": "15.86",
      "AUD": "1.46",
      "JPY": "123.95",
      "NZD": "1.52",
      "TRY": "10.14",
      "BRL": "5.99",
      "CAD": "1.34",
      "CNY": "6.96",
      "HKD": "8.45",
      "HUF": "336.96",
      "INR": "81.38",
      "RUB": "77.18",
      "ILS": "3.49",
      "MYR": "4.53",
      "MXN": "22.1",
      "SGD": "1.46",
      "RON": "4.61",
      "IDR": "15286.14",
      "PHP": "55.04",
      "ARS": "107.78",
      "THB": "36.21",
      "NGN": "448.07",
      "PKR": "186.8",
      "AED": "3.99",
      "UAH": "28.5",
      "BGN": "1.82",
      "HRK": "7.0",
      "RSD": "109.85",
      "CLP": "887.55",
      "KRW": "1281.48",
      "EGP": "17.05",
      "SAR": "4.07",
      "QAR": "3.95"
    },
    "ZAR": {
      "USD": "0.07",
      "EUR": "0.06",
      "GBP": "0.0497",
      "PLN": "0.27",
      "CZK": "1.5",
      "SEK": "0.59",
      "NOK": "0.57",
      "DKK": "0.44",
      "CHF": "0.06",
      "ZAR": "1.0",
      "AUD": "0.09",
      "JPY": "7.82",
      "NZD": "0.1",
      "TRY": "0.64",
      "BRL": "0.38",
      "CAD": "0.08",
      "CNY": "0.44",
      "HKD": "0.53",
      "HUF": "21.25",
      "INR": "5.13",
      "RUB": "4.87",
      "ILS": "0.22",
      "MYR": "0.29",
      "MXN": "1.39",
      "SGD": "0.09",
      "RON": "0.29",
      "IDR": "963.87",
      "PHP": "3.47",
      "ARS": "6.8",
      "THB": "2.28",
      "NGN": "28.25",
      "PKR": "11.78",
      "AED": "0.25",
      "UAH": "1.8",
      "BGN": "0.11",
      "HRK": "0.44",
      "RSD": "6.93",
      "CLP": "55.96",
      "KRW": "80.8",
      "EGP": "1.08",
      "SAR": "0.26",
      "QAR": "0.25"
    },
    "AUD": {
      "USD": "0.75",
      "EUR": "0.64",
      "GBP": "0.54",
      "PLN": "2.94",
      "CZK": "16.32",
      "SEK": "6.43",
      "NOK": "6.25",
      "DKK": "4.77",
      "CHF": "0.69",
      "ZAR": "10.9",
      "AUD": "1.0",
      "JPY": "85.17",
      "NZD": "1.05",
      "TRY": "6.97",
      "BRL": "4.11",
      "CAD": "0.92",
      "CNY": "4.78",
      "HKD": "5.81",
      "HUF": "231.56",
      "INR": "55.92",
      "RUB": "53.04",
      "ILS": "2.4",
      "MYR": "3.11",
      "MXN": "15.19",
      "SGD": "1.0",
      "RON": "3.17",
      "IDR": "10504.43",
      "PHP": "37.82",
      "ARS": "74.07",
      "THB": "24.89",
      "NGN": "307.91",
      "PKR": "128.37",
      "AED": "2.74",
      "UAH": "19.58",
      "BGN": "1.25",
      "HRK": "4.81",
      "RSD": "75.49",
      "CLP": "609.91",
      "KRW": "880.61",
      "EGP": "11.72",
      "SAR": "2.8",
      "QAR": "2.72"
    },
    "JPY": {
      "USD": "0.0088",
      "EUR": "0.0075",
      "GBP": "0.0064",
      "PLN": "0.0345",
      "CZK": "0.19",
      "SEK": "0.08",
      "NOK": "0.07",
      "DKK": "0.06",
      "CHF": "0.0081",
      "ZAR": "0.13",
      "AUD": "0.0117",
      "JPY": "1.0",
      "NZD": "0.0123",
      "TRY": "0.08",
      "BRL": "0.0483",
      "CAD": "0.0108",
      "CNY": "0.06",
      "HKD": "0.07",
      "HUF": "2.72",
      "INR": "0.66",
      "RUB": "0.62",
      "ILS": "0.0282",
      "MYR": "0.0366",
      "MXN": "0.18",
      "SGD": "0.0118",
      "RON": "0.0372",
      "IDR": "123.33",
      "PHP": "0.44",
      "ARS": "0.87",
      "THB": "0.29",
      "NGN": "3.62",
      "PKR": "1.51",
      "AED": "0.0322",
      "UAH": "0.23",
      "BGN": "0.0147",
      "HRK": "0.06",
      "RSD": "0.89",
      "CLP": "7.16",
      "KRW": "10.34",
      "EGP": "0.14",
      "SAR": "0.0329",
      "QAR": "0.0319"
    },
    "NZD": {
      "USD": "0.71",
      "EUR": "0.61",
      "GBP": "0.52",
      "PLN": "2.81",
      "CZK": "15.6",
      "SEK": "6.15",
      "NOK": "5.97",
      "DKK": "4.56",
      "CHF": "0.66",
      "ZAR": "10.42",
      "AUD": "0.96",
      "JPY": "81.43",
      "NZD": "1.0",
      "TRY": "6.66",
      "BRL": "3.93",
      "CAD": "0.88",
      "CNY": "4.57",
      "HKD": "5.55",
      "HUF": "221.37",
      "INR": "53.46",
      "RUB": "50.7",
      "ILS": "2.29",
      "MYR": "2.98",
      "MXN": "14.52",
      "SGD": "0.96",
      "RON": "3.03",
      "IDR": "10042.28",
      "PHP": "36.16",
      "ARS": "70.81",
      "THB": "23.79",
      "NGN": "294.36",
      "PKR": "122.72",
      "AED": "2.62",
      "UAH": "18.72",
      "BGN": "1.2",
      "HRK": "4.6",
      "RSD": "72.16",
      "CLP": "583.08",
      "KRW": "841.87",
      "EGP": "11.2",
      "SAR": "2.68",
      "QAR": "2.6"
    },
    "TRY": {
      "USD": "0.11",
      "EUR": "0.09",
      "GBP": "0.08",
      "PLN": "0.42",
      "CZK": "2.34",
      "SEK": "0.92",
      "NOK": "0.9",
      "DKK": "0.68",
      "CHF": "0.1",
      "ZAR": "1.56",
      "AUD": "0.14",
      "JPY": "12.22",
      "NZD": "0.15",
      "TRY": "1.0",
      "BRL": "0.59",
      "CAD": "0.13",
      "CNY": "0.69",
      "HKD": "0.83",
      "HUF": "33.22",
      "INR": "8.02",
      "RUB": "7.61",
      "ILS": "0.34",
      "MYR": "0.45",
      "MXN": "2.18",
      "SGD": "0.14",
      "RON": "0.45",
      "IDR": "1506.87",
      "PHP": "5.43",
      "ARS": "10.62",
      "THB": "3.57",
      "NGN": "44.17",
      "PKR": "18.41",
      "AED": "0.39",
      "UAH": "2.81",
      "BGN": "0.18",
      "HRK": "0.69",
      "RSD": "10.83",
      "CLP": "87.49",
      "KRW": "126.32",
      "EGP": "1.68",
      "SAR": "0.4",
      "QAR": "0.39"
    },
    "BRL": {
      "USD": "0.18",
      "EUR": "0.16",
      "GBP": "0.13",
      "PLN": "0.71",
      "CZK": "3.97",
      "SEK": "1.56",
      "NOK": "1.52",
      "DKK": "1.16",
      "CHF": "0.17",
      "ZAR": "2.65",
      "AUD": "0.24",
      "JPY": "20.7",
      "NZD": "0.25",
      "TRY": "1.69",
      "BRL": "1.0",
      "CAD": "0.22",
      "CNY": "1.16",
      "HKD": "1.41",
      "HUF": "56.29",
      "INR": "13.59",
      "RUB": "12.89",
      "ILS": "0.58",
      "MYR": "0.76",
      "MXN": "3.69",
      "SGD": "0.24",
      "RON": "0.77",
      "IDR": "2553.4",
      "PHP": "9.19",
      "ARS": "18.0",
      "THB": "6.05",
      "NGN": "74.85",
      "PKR": "31.2",
      "AED": "0.67",
      "UAH": "4.76",
      "BGN": "0.3",
      "HRK": "1.17",
      "RSD": "18.35",
      "CLP": "148.26",
      "KRW": "214.06",
      "EGP": "2.85",
      "SAR": "0.68",
      "QAR": "0.66"
    },
    "CAD": {
      "USD": "0.81",
      "EUR": "0.7",
      "GBP": "0.59",
      "PLN": "3.19",
      "CZK": "17.73",
      "SEK": "6.99",
      "NOK": "6.78",
      "DKK": "5.18",
      "CHF": "0.75",
      "ZAR": "11.84",
      "AUD": "1.09",
      "JPY": "92.51",
      "NZD": "1.14",
      "TRY": "7.57",
      "BRL": "4.47",
      "CAD": "1.0",
      "CNY": "5.19",
      "HKD": "6.31",
      "HUF": "251.5",
      "INR": "60.74",
      "RUB": "57.61",
      "ILS": "2.6",
      "MYR": "3.38",
      "MXN": "16.49",
      "SGD": "1.09",
      "RON": "3.44",
      "IDR": "11409.0",
      "PHP": "41.08",
      "ARS": "80.44",
      "THB": "27.03",
      "NGN": "334.42",
      "PKR": "139.42",
      "AED": "2.98",
      "UAH": "21.27",
      "BGN": "1.36",
      "HRK": "5.22",
      "RSD": "81.99",
      "CLP": "662.43",
      "KRW": "956.45",
      "EGP": "12.73",
      "SAR": "3.04",
      "QAR": "2.95"
    },
    "HKD": {
      "USD": "0.13",
      "EUR": "0.11",
      "GBP": "0.09",
      "PLN": "0.51",
      "CZK": "2.81",
      "SEK": "1.11",
      "NOK": "1.08",
      "DKK": "0.82",
      "CHF": "0.12",
      "ZAR": "1.88",
      "AUD": "0.17",
      "JPY": "14.67",
      "NZD": "0.18",
      "TRY": "1.2",
      "BRL": "0.71",
      "CAD": "0.16",
      "CNY": "0.82",
      "HKD": "1.0",
      "HUF": "39.88",
      "INR": "9.63",
      "RUB": "9.14",
      "ILS": "0.41",
      "MYR": "0.54",
      "MXN": "2.62",
      "SGD": "0.17",
      "RON": "0.55",
      "IDR": "1809.24",
      "PHP": "6.51",
      "ARS": "12.76",
      "THB": "4.29",
      "NGN": "53.03",
      "PKR": "22.11",
      "AED": "0.47",
      "UAH": "3.37",
      "BGN": "0.22",
      "HRK": "0.83",
      "RSD": "13.0",
      "CLP": "105.05",
      "KRW": "151.67",
      "EGP": "2.02",
      "SAR": "0.48",
      "QAR": "0.47"
    },
    "HUF": {
      "USD": "0.0032",
      "EUR": "0.0028",
      "GBP": "0.0023",
      "PLN": "0.0127",
      "CZK": "0.07",
      "SEK": "0.0278",
      "NOK": "0.027",
      "DKK": "0.0206",
      "CHF": "0.003",
      "ZAR": "0.0471",
      "AUD": "0.0043",
      "JPY": "0.37",
      "NZD": "0.0045",
      "TRY": "0.0301",
      "BRL": "0.0178",
      "CAD": "0.004",
      "CNY": "0.0206",
      "HKD": "0.0251",
      "HUF": "1.0",
      "INR": "0.24",
      "RUB": "0.23",
      "ILS": "0.0104",
      "MYR": "0.0134",
      "MXN": "0.07",
      "SGD": "0.0043",
      "RON": "0.0137",
      "IDR": "45.36",
      "PHP": "0.16",
      "ARS": "0.32",
      "THB": "0.11",
      "NGN": "1.33",
      "PKR": "0.55",
      "AED": "0.0118",
      "UAH": "0.08",
      "BGN": "0.0054",
      "HRK": "0.0208",
      "RSD": "0.33",
      "CLP": "2.63",
      "KRW": "3.8",
      "EGP": "0.05",
      "SAR": "0.0121",
      "QAR": "0.0117"
    },
    "INR": {
      "USD": "0.0133",
      "EUR": "0.0115",
      "GBP": "0.0097",
      "PLN": "0.05",
      "CZK": "0.29",
      "SEK": "0.12",
      "NOK": "0.11",
      "DKK": "0.09",
      "CHF": "0.0123",
      "ZAR": "0.19",
      "AUD": "0.0179",
      "JPY": "1.52",
      "NZD": "0.0187",
      "TRY": "0.12",
      "BRL": "0.07",
      "CAD": "0.0165",
      "CNY": "0.09",
      "HKD": "0.1",
      "HUF": "4.14",
      "INR": "1.0",
      "RUB": "0.95",
      "ILS": "0.0429",
      "MYR": "0.06",
      "MXN": "0.27",
      "SGD": "0.018",
      "RON": "0.06",
      "IDR": "187.83",
      "PHP": "0.68",
      "ARS": "1.32",
      "THB": "0.44",
      "NGN": "5.51",
      "PKR": "2.3",
      "AED": "0.049",
      "UAH": "0.35",
      "BGN": "0.0224",
      "HRK": "0.09",
      "RSD": "1.35",
      "CLP": "10.91",
      "KRW": "15.75",
      "EGP": "0.21",
      "SAR": "0.05",
      "QAR": "0.0486"
    },
    "RUB": {
      "USD": "0.0141",
      "EUR": "0.0121",
      "GBP": "0.0102",
      "PLN": "0.06",
      "CZK": "0.31",
      "SEK": "0.12",
      "NOK": "0.12",
      "DKK": "0.09",
      "CHF": "0.013",
      "ZAR": "0.21",
      "AUD": "0.0189",
      "JPY": "1.61",
      "NZD": "0.0197",
      "TRY": "0.13",
      "BRL": "0.08",
      "CAD": "0.0174",
      "CNY": "0.09",
      "HKD": "0.11",
      "HUF": "4.37",
      "INR": "1.05",
      "RUB": "1.0",
      "ILS": "0.0452",
      "MYR": "0.06",
      "MXN": "0.29",
      "SGD": "0.0189",
      "RON": "0.06",
      "IDR": "198.05",
      "PHP": "0.71",
      "ARS": "1.4",
      "THB": "0.47",
      "NGN": "5.81",
      "PKR": "2.42",
      "AED": "0.05",
      "UAH": "0.37",
      "BGN": "0.0236",
      "HRK": "0.09",
      "RSD": "1.42",
      "CLP": "11.5",
      "KRW": "16.6",
      "EGP": "0.22",
      "SAR": "0.05",
      "QAR": "0.05"
    },
    "ILS": {
      "USD": "0.31",
      "EUR": "0.27",
      "GBP": "0.23",
      "PLN": "1.23",
      "CZK": "6.81",
      "SEK": "2.68",
      "NOK": "2.6",
      "DKK": "1.99",
      "CHF": "0.29",
      "ZAR": "4.54",
      "AUD": "0.42",
      "JPY": "35.51",
      "NZD": "0.44",
      "TRY": "2.91",
      "BRL": "1.72",
      "CAD": "0.38",
      "CNY": "1.99",
      "HKD": "2.42",
      "HUF": "96.55",
      "INR": "23.32",
      "RUB": "22.11",
      "ILS": "1.0",
      "MYR": "1.3",
      "MXN": "6.33",
      "SGD": "0.42",
      "RON": "1.32",
      "IDR": "4379.81",
      "PHP": "15.77",
      "ARS": "30.88",
      "THB": "10.38",
      "NGN": "128.38",
      "PKR": "53.52",
      "AED": "1.14",
      "UAH": "8.16",
      "BGN": "0.52",
      "HRK": "2.01",
      "RSD": "31.47",
      "CLP": "254.3",
      "KRW": "367.17",
      "EGP": "4.89",
      "SAR": "1.17",
      "QAR": "1.13"
    },
    "MYR": {
      "USD": "0.24",
      "EUR": "0.21",
      "GBP": "0.17",
      "PLN": "0.94",
      "CZK": "5.24",
      "SEK": "2.07",
      "NOK": "2.01",
      "DKK": "1.53",
      "CHF": "0.22",
      "ZAR": "3.5",
      "AUD": "0.32",
      "JPY": "27.36",
      "NZD": "0.34",
      "TRY": "2.24",
      "BRL": "1.32",
      "CAD": "0.3",
      "CNY": "1.54",
      "HKD": "1.86",
      "HUF": "74.37",
      "INR": "17.96",
      "RUB": "17.03",
      "ILS": "0.77",
      "MYR": "1.0",
      "MXN": "4.88",
      "SGD": "0.32",
      "RON": "1.02",
      "IDR": "3373.68",
      "PHP": "12.15",
      "ARS": "23.79",
      "THB": "7.99",
      "NGN": "98.89",
      "PKR": "41.23",
      "AED": "0.88",
      "UAH": "6.29",
      "BGN": "0.4",
      "HRK": "1.54",
      "RSD": "24.24",
      "CLP": "195.88",
      "KRW": "282.82",
      "EGP": "3.76",
      "SAR": "0.9",
      "QAR": "0.87"
    },
    "MXN": {
      "USD": "0.0491",
      "EUR": "0.0422",
      "GBP": "0.0357",
      "PLN": "0.19",
      "CZK": "1.07",
      "SEK": "0.42",
      "NOK": "0.41",
      "DKK": "0.31",
      "CHF": "0.0453",
      "ZAR": "0.72",
      "AUD": "0.07",
      "JPY": "5.61",
      "NZD": "0.07",
      "TRY": "0.46",
      "BRL": "0.27",
      "CAD": "0.06",
      "CNY": "0.31",
      "HKD": "0.38",
      "HUF": "15.25",
      "INR": "3.68",
      "RUB": "3.49",
      "ILS": "0.16",
      "MYR": "0.21",
      "MXN": "1.0",
      "SGD": "0.07",
      "RON": "0.21",
      "IDR": "691.69",
      "PHP": "2.49",
      "ARS": "4.88",
      "THB": "1.64",
      "NGN": "20.28",
      "PKR": "8.45",
      "AED": "0.18",
      "UAH": "1.29",
      "BGN": "0.08",
      "HRK": "0.32",
      "RSD": "4.97",
      "CLP": "40.16",
      "KRW": "57.99",
      "EGP": "0.77",
      "SAR": "0.18",
      "QAR": "0.18"
    },
    "SGD": {
      "USD": "0.74",
      "EUR": "0.64",
      "GBP": "0.54",
      "PLN": "2.93",
      "CZK": "16.26",
      "SEK": "6.41",
      "NOK": "6.22",
      "DKK": "4.75",
      "CHF": "0.68",
      "ZAR": "10.86",
      "AUD": "1.0",
      "JPY": "84.84",
      "NZD": "1.04",
      "TRY": "6.94",
      "BRL": "4.1",
      "CAD": "0.92",
      "CNY": "4.76",
      "HKD": "5.78",
      "HUF": "230.65",
      "INR": "55.71",
      "RUB": "52.83",
      "ILS": "2.39",
      "MYR": "3.1",
      "MXN": "15.13",
      "SGD": "1.0",
      "RON": "3.16",
      "IDR": "10463.38",
      "PHP": "37.68",
      "ARS": "73.78",
      "THB": "24.79",
      "NGN": "306.71",
      "PKR": "127.87",
      "AED": "2.73",
      "UAH": "19.51",
      "BGN": "1.25",
      "HRK": "4.79",
      "RSD": "75.19",
      "CLP": "607.53",
      "KRW": "877.17",
      "EGP": "11.67",
      "SAR": "2.79",
      "QAR": "2.71"
    },
    "RON": {
      "USD": "0.24",
      "EUR": "0.2",
      "GBP": "0.17",
      "PLN": "0.93",
      "CZK": "5.15",
      "SEK": "2.03",
      "NOK": "1.97",
      "DKK": "1.5",
      "CHF": "0.22",
      "ZAR": "3.44",
      "AUD": "0.32",
      "JPY": "26.86",
      "NZD": "0.33",
      "TRY": "2.2",
      "BRL": "1.3",
      "CAD": "0.29",
      "CNY": "1.51",
      "HKD": "1.83",
      "HUF": "73.03",
      "INR": "17.64",
      "RUB": "16.73",
      "ILS": "0.76",
      "MYR": "0.98",
      "MXN": "4.79",
      "SGD": "0.32",
      "RON": "1.0",
      "IDR": "3313.08",
      "PHP": "11.93",
      "ARS": "23.36",
      "THB": "7.85",
      "NGN": "97.11",
      "PKR": "40.49",
      "AED": "0.86",
      "UAH": "6.18",
      "BGN": "0.4",
      "HRK": "1.52",
      "RSD": "23.81",
      "CLP": "192.37",
      "KRW": "277.74",
      "EGP": "3.7",
      "SAR": "0.88",
      "QAR": "0.86"
    },
    "IDR": {
      "USD": "0.0001",
      "EUR": "0.0001",
      "GBP": "0.0001",
      "PLN": "0.0003",
      "CZK": "0.0016",
      "SEK": "0.0006",
      "NOK": "0.0006",
      "DKK": "0.0005",
      "CHF": "0.0001",
      "ZAR": "0.001",
      "AUD": "0.0001",
      "JPY": "0.0081",
      "NZD": "0.0001",
      "TRY": "0.0007",
      "BRL": "0.0004",
      "CAD": "0.0001",
      "CNY": "0.0005",
      "HKD": "0.0006",
      "HUF": "0.022",
      "INR": "0.0053",
      "RUB": "0.005",
      "ILS": "0.0002",
      "MYR": "0.0003",
      "MXN": "0.0014",
      "SGD": "0.0001",
      "RON": "0.0003",
      "IDR": "1.0",
      "PHP": "0.0036",
      "ARS": "0.0071",
      "THB": "0.0024",
      "NGN": "0.0293",
      "PKR": "0.0122",
      "AED": "0.0003",
      "UAH": "0.0019",
      "BGN": "0.0001",
      "HRK": "0.0005",
      "RSD": "0.0072",
      "CLP": "0.06",
      "KRW": "0.08",
      "EGP": "0.0011",
      "SAR": "0.0003",
      "QAR": "0.0003"
    },
    "PHP": {
      "USD": "0.0197",
      "EUR": "0.0169",
      "GBP": "0.0143",
      "PLN": "0.08",
      "CZK": "0.43",
      "SEK": "0.17",
      "NOK": "0.17",
      "DKK": "0.13",
      "CHF": "0.0182",
      "ZAR": "0.29",
      "AUD": "0.0264",
      "JPY": "2.25",
      "NZD": "0.0277",
      "TRY": "0.18",
      "BRL": "0.11",
      "CAD": "0.0243",
      "CNY": "0.13",
      "HKD": "0.15",
      "HUF": "6.12",
      "INR": "1.48",
      "RUB": "1.4",
      "ILS": "0.06",
      "MYR": "0.08",
      "MXN": "0.4",
      "SGD": "0.0265",
      "RON": "0.08",
      "IDR": "277.71",
      "PHP": "1.0",
      "ARS": "1.96",
      "THB": "0.66",
      "NGN": "8.14",
      "PKR": "3.39",
      "AED": "0.07",
      "UAH": "0.52",
      "BGN": "0.0331",
      "HRK": "0.13",
      "RSD": "2.0",
      "CLP": "16.12",
      "KRW": "23.28",
      "EGP": "0.31",
      "SAR": "0.07",
      "QAR": "0.07"
    },
    "ARS": {
      "USD": "0.0101",
      "EUR": "0.0087",
      "GBP": "0.0073",
      "PLN": "0.0397",
      "CZK": "0.22",
      "SEK": "0.09",
      "NOK": "0.08",
      "DKK": "0.06",
      "CHF": "0.0093",
      "ZAR": "0.15",
      "AUD": "0.0135",
      "JPY": "1.15",
      "NZD": "0.0141",
      "TRY": "0.09",
      "BRL": "0.06",
      "CAD": "0.0124",
      "CNY": "0.06",
      "HKD": "0.08",
      "HUF": "3.13",
      "INR": "0.76",
      "RUB": "0.72",
      "ILS": "0.0324",
      "MYR": "0.042",
      "MXN": "0.21",
      "SGD": "0.0136",
      "RON": "0.0428",
      "IDR": "141.82",
      "PHP": "0.51",
      "ARS": "1.0",
      "THB": "0.34",
      "NGN": "4.16",
      "PKR": "1.73",
      "AED": "0.037",
      "UAH": "0.26",
      "BGN": "0.0169",
      "HRK": "0.06",
      "RSD": "1.02",
      "CLP": "8.23",
      "KRW": "11.89",
      "EGP": "0.16",
      "SAR": "0.0378",
      "QAR": "0.0367"
    },
    "THB": {
      "USD": "0.03",
      "EUR": "0.0257",
      "GBP": "0.0218",
      "PLN": "0.12",
      "CZK": "0.66",
      "SEK": "0.26",
      "NOK": "0.25",
      "DKK": "0.19",
      "CHF": "0.0276",
      "ZAR": "0.44",
      "AUD": "0.0402",
      "JPY": "3.42",
      "NZD": "0.042",
      "TRY": "0.28",
      "BRL": "0.17",
      "CAD": "0.037",
      "CNY": "0.19",
      "HKD": "0.23",
      "HUF": "9.3",
      "INR": "2.25",
      "RUB": "2.13",
      "ILS": "0.1",
      "MYR": "0.13",
      "MXN": "0.61",
      "SGD": "0.0403",
      "RON": "0.13",
      "IDR": "422.11",
      "PHP": "1.52",
      "ARS": "2.98",
      "THB": "1.0",
      "NGN": "12.37",
      "PKR": "5.16",
      "AED": "0.11",
      "UAH": "0.79",
      "BGN": "0.05",
      "HRK": "0.19",
      "RSD": "3.03",
      "CLP": "24.51",
      "KRW": "35.39",
      "EGP": "0.47",
      "SAR": "0.11",
      "QAR": "0.11"
    },
    "NGN": {
      "USD": "0.0024",
      "EUR": "0.0021",
      "GBP": "0.0018",
      "PLN": "0.0095",
      "CZK": "0.05",
      "SEK": "0.0209",
      "NOK": "0.0203",
      "DKK": "0.0155",
      "CHF": "0.0022",
      "ZAR": "0.0354",
      "AUD": "0.0032",
      "JPY": "0.28",
      "NZD": "0.0034",
      "TRY": "0.0226",
      "BRL": "0.0134",
      "CAD": "0.003",
      "CNY": "0.0155",
      "HKD": "0.0189",
      "HUF": "0.75",
      "INR": "0.18",
      "RUB": "0.17",
      "ILS": "0.0078",
      "MYR": "0.0101",
      "MXN": "0.0493",
      "SGD": "0.0033",
      "RON": "0.0103",
      "IDR": "34.12",
      "PHP": "0.12",
      "ARS": "0.24",
      "THB": "0.08",
      "NGN": "1.0",
      "PKR": "0.42",
      "AED": "0.0089",
      "UAH": "0.06",
      "BGN": "0.0041",
      "HRK": "0.0156",
      "RSD": "0.25",
      "CLP": "1.98",
      "KRW": "2.86",
      "EGP": "0.0381",
      "SAR": "0.0091",
      "QAR": "0.0088"
    },
    "PKR": {
      "USD": "0.0058",
      "EUR": "0.005",
      "GBP": "0.0042",
      "PLN": "0.0229",
      "CZK": "0.13",
      "SEK": "0.05",
      "NOK": "0.0487",
      "DKK": "0.0371",
      "CHF": "0.0054",
      "ZAR": "0.08",
      "AUD": "0.0078",
      "JPY": "0.66",
      "NZD": "0.0081",
      "TRY": "0.05",
      "BRL": "0.032",
      "CAD": "0.0072",
      "CNY": "0.0372",
      "HKD": "0.0452",
      "HUF": "1.8",
      "INR": "0.44",
      "RUB": "0.41",
      "ILS": "0.0187",
      "MYR": "0.0243",
      "MXN": "0.12",
      "SGD": "0.0078",
      "RON": "0.0247",
      "IDR": "81.83",
      "PHP": "0.29",
      "ARS": "0.58",
      "THB": "0.19",
      "NGN": "2.4",
      "PKR": "1.0",
      "AED": "0.0214",
      "UAH": "0.15",
      "BGN": "0.0098",
      "HRK": "0.0375",
      "RSD": "0.59",
      "CLP": "4.75",
      "KRW": "6.86",
      "EGP": "0.09",
      "SAR": "0.0218",
      "QAR": "0.0212"
    },
    "AED": {
      "USD": "0.27",
      "EUR": "0.23",
      "GBP": "0.2",
      "PLN": "1.07",
      "CZK": "5.95",
      "SEK": "2.35",
      "NOK": "2.28",
      "DKK": "1.74",
      "CHF": "0.25",
      "ZAR": "3.97",
      "AUD": "0.36",
      "JPY": "31.07",
      "NZD": "0.38",
      "TRY": "2.54",
      "BRL": "1.5",
      "CAD": "0.34",
      "CNY": "1.74",
      "HKD": "2.12",
      "HUF": "84.46",
      "INR": "20.4",
      "RUB": "19.34",
      "ILS": "0.87",
      "MYR": "1.14",
      "MXN": "5.54",
      "SGD": "0.37",
      "RON": "1.16",
      "IDR": "3831.35",
      "PHP": "13.8",
      "ARS": "27.01",
      "THB": "9.08",
      "NGN": "112.31",
      "PKR": "46.82",
      "AED": "1.0",
      "UAH": "7.14",
      "BGN": "0.46",
      "HRK": "1.75",
      "RSD": "27.53",
      "CLP": "222.46",
      "KRW": "321.19",
      "EGP": "4.27",
      "SAR": "1.02",
      "QAR": "0.99"
    },
    "UAH": {
      "USD": "0.0381",
      "EUR": "0.0327",
      "GBP": "0.0277",
      "PLN": "0.15",
      "CZK": "0.83",
      "SEK": "0.33",
      "NOK": "0.32",
      "DKK": "0.24",
      "CHF": "0.0351",
      "ZAR": "0.56",
      "AUD": "0.05",
      "JPY": "4.35",
      "NZD": "0.05",
      "TRY": "0.36",
      "BRL": "0.21",
      "CAD": "0.047",
      "CNY": "0.24",
      "HKD": "0.3",
      "HUF": "11.82",
      "INR": "2.86",
      "RUB": "2.71",
      "ILS": "0.12",
      "MYR": "0.16",
      "MXN": "0.78",
      "SGD": "0.05",
      "RON": "0.16",
      "IDR": "536.42",
      "PHP": "1.93",
      "ARS": "3.78",
      "THB": "1.27",
      "NGN": "15.72",
      "PKR": "6.56",
      "AED": "0.14",
      "UAH": "1.0",
      "BGN": "0.06",
      "HRK": "0.25",
      "RSD": "3.85",
      "CLP": "31.15",
      "KRW": "44.97",
      "EGP": "0.6",
      "SAR": "0.14",
      "QAR": "0.14"
    },
    "BGN": {
      "USD": "0.6",
      "EUR": "0.51",
      "GBP": "0.43",
      "PLN": "2.34",
      "CZK": "13.02",
      "SEK": "5.13",
      "NOK": "4.98",
      "DKK": "3.8",
      "CHF": "0.55",
      "ZAR": "8.7",
      "AUD": "0.8",
      "JPY": "67.97",
      "NZD": "0.83",
      "TRY": "5.56",
      "BRL": "3.28",
      "CAD": "0.73",
      "CNY": "3.82",
      "HKD": "4.63",
      "HUF": "184.78",
      "INR": "44.63",
      "RUB": "42.32",
      "ILS": "1.91",
      "MYR": "2.48",
      "MXN": "12.12",
      "SGD": "0.8",
      "RON": "2.53",
      "IDR": "8382.29",
      "PHP": "30.18",
      "ARS": "59.1",
      "THB": "19.86",
      "NGN": "245.7",
      "PKR": "102.44",
      "AED": "2.19",
      "UAH": "15.63",
      "BGN": "1.0",
      "HRK": "3.84",
      "RSD": "60.24",
      "CLP": "486.7",
      "KRW": "702.71",
      "EGP": "9.35",
      "SAR": "2.23",
      "QAR": "2.17"
    },
    "CLP": {
      "USD": "0.0012",
      "EUR": "0.0011",
      "GBP": "0.0009",
      "PLN": "0.0048",
      "CZK": "0.0268",
      "SEK": "0.0105",
      "NOK": "0.0102",
      "DKK": "0.0078",
      "CHF": "0.0011",
      "ZAR": "0.0179",
      "AUD": "0.0016",
      "JPY": "0.14",
      "NZD": "0.0017",
      "TRY": "0.0114",
      "BRL": "0.0067",
      "CAD": "0.0015",
      "CNY": "0.0078",
      "HKD": "0.0095",
      "HUF": "0.38",
      "INR": "0.09",
      "RUB": "0.09",
      "ILS": "0.0039",
      "MYR": "0.0051",
      "MXN": "0.0249",
      "SGD": "0.0016",
      "RON": "0.0052",
      "IDR": "17.22",
      "PHP": "0.06",
      "ARS": "0.12",
      "THB": "0.0408",
      "NGN": "0.5",
      "PKR": "0.21",
      "AED": "0.0045",
      "UAH": "0.0321",
      "BGN": "0.0021",
      "HRK": "0.0079",
      "RSD": "0.12",
      "CLP": "1.0",
      "KRW": "1.44",
      "EGP": "0.0192",
      "SAR": "0.0046",
      "QAR": "0.0045"
    },
    "KRW": {
      "USD": "0.0008",
      "EUR": "0.0007",
      "GBP": "0.0006",
      "PLN": "0.0033",
      "CZK": "0.0185",
      "SEK": "0.0073",
      "NOK": "0.0071",
      "DKK": "0.0054",
      "CHF": "0.0008",
      "ZAR": "0.0124",
      "AUD": "0.0011",
      "JPY": "0.1",
      "NZD": "0.0012",
      "TRY": "0.0079",
      "BRL": "0.0047",
      "CAD": "0.001",
      "CNY": "0.0054",
      "HKD": "0.0066",
      "HUF": "0.26",
      "INR": "0.06",
      "RUB": "0.06",
      "ILS": "0.0027",
      "MYR": "0.0035",
      "MXN": "0.0172",
      "SGD": "0.0011",
      "RON": "0.0036",
      "IDR": "11.93",
      "PHP": "0.043",
      "ARS": "0.08",
      "THB": "0.0283",
      "NGN": "0.35",
      "PKR": "0.15",
      "AED": "0.0031",
      "UAH": "0.0222",
      "BGN": "0.0014",
      "HRK": "0.0055",
      "RSD": "0.09",
      "CLP": "0.69",
      "KRW": "1.0",
      "EGP": "0.0133",
      "SAR": "0.0032",
      "QAR": "0.0031"
    },
    "EGP": {
      "USD": "0.06",
      "EUR": "0.05",
      "GBP": "0.0463",
      "PLN": "0.25",
      "CZK": "1.39",
      "SEK": "0.55",
      "NOK": "0.53",
      "DKK": "0.41",
      "CHF": "0.06",
      "ZAR": "0.93",
      "AUD": "0.09",
      "JPY": "7.27",
      "NZD": "0.09",
      "TRY": "0.59",
      "BRL": "0.35",
      "CAD": "0.08",
      "CNY": "0.41",
      "HKD": "0.5",
      "HUF": "19.76",
      "INR": "4.77",
      "RUB": "4.53",
      "ILS": "0.2",
      "MYR": "0.27",
      "MXN": "1.3",
      "SGD": "0.09",
      "RON": "0.27",
      "IDR": "896.56",
      "PHP": "3.23",
      "ARS": "6.32",
      "THB": "2.12",
      "NGN": "26.28",
      "PKR": "10.96",
      "AED": "0.23",
      "UAH": "1.67",
      "BGN": "0.11",
      "HRK": "0.41",
      "RSD": "6.44",
      "CLP": "52.06",
      "KRW": "75.16",
      "EGP": "1.0",
      "SAR": "0.24",
      "QAR": "0.23"
    },
    "SAR": {
      "USD": "0.27",
      "EUR": "0.23",
      "GBP": "0.19",
      "PLN": "1.05",
      "CZK": "5.83",
      "SEK": "2.3",
      "NOK": "2.23",
      "DKK": "1.7",
      "CHF": "0.25",
      "ZAR": "3.89",
      "AUD": "0.36",
      "JPY": "30.43",
      "NZD": "0.37",
      "TRY": "2.49",
      "BRL": "1.47",
      "CAD": "0.33",
      "CNY": "1.71",
      "HKD": "2.07",
      "HUF": "82.72",
      "INR": "19.98",
      "RUB": "18.95",
      "ILS": "0.86",
      "MYR": "1.11",
      "MXN": "5.42",
      "SGD": "0.36",
      "RON": "1.13",
      "IDR": "3752.41",
      "PHP": "13.51",
      "ARS": "26.46",
      "THB": "8.89",
      "NGN": "109.99",
      "PKR": "45.86",
      "AED": "0.98",
      "UAH": "7.0",
      "BGN": "0.45",
      "HRK": "1.72",
      "RSD": "26.97",
      "CLP": "217.87",
      "KRW": "314.57",
      "EGP": "4.19",
      "SAR": "1.0",
      "QAR": "0.97"
    },
    "QAR": {
      "USD": "0.27",
      "EUR": "0.24",
      "GBP": "0.2",
      "PLN": "1.08",
      "CZK": "6.01",
      "SEK": "2.37",
      "NOK": "2.3",
      "DKK": "1.75",
      "CHF": "0.25",
      "ZAR": "4.01",
      "AUD": "0.37",
      "JPY": "31.34",
      "NZD": "0.38",
      "TRY": "2.57",
      "BRL": "1.51",
      "CAD": "0.34",
      "CNY": "1.76",
      "HKD": "2.14",
      "HUF": "85.2",
      "INR": "20.58",
      "RUB": "19.52",
      "ILS": "0.88",
      "MYR": "1.15",
      "MXN": "5.59",
      "SGD": "0.37",
      "RON": "1.17",
      "IDR": "3865.23",
      "PHP": "13.92",
      "ARS": "27.25",
      "THB": "9.16",
      "NGN": "113.3",
      "PKR": "47.24",
      "AED": "1.01",
      "UAH": "7.21",
      "BGN": "0.46",
      "HRK": "1.77",
      "RSD": "27.78",
      "CLP": "224.42",
      "KRW": "324.03",
      "EGP": "4.31",
      "SAR": "1.03",
      "QAR": "1.0"
    }
  },
  "trader": {
    "buy": {
      "BTC": { "EUR": "53406.8" },
      "LTC": { "EUR": "162.45" },
      "ETH": { "EUR": "3265.01" },
      "BCH": { "EUR": "531.06" },
      "XRP": { "EUR": "0.9356" },
      "NANO": { "EUR": "4.53" },
      "TRX": { "EUR": "0.0846" },
      "DAI": { "EUR": "0.8575" },
      "ETC": { "EUR": "45.21" },
      "DOGE": { "EUR": "0.212" },
      "XLM": { "EUR": "0.3254" },
      "BNB": { "EUR": "421.3" },
      "LINK": { "EUR": "22.27" },
      "AVA": { "EUR": "2.67" },
      "VET": { "EUR": "0.1015" },
      "BTCV": { "EUR": "6.52" },
      "DOT": { "EUR": "35.19" },
      "MATIC": { "EUR": "1.28" },
      "ADA": { "EUR": "1.83" },
      "UNI": { "EUR": "22.25" },
      "SOL": { "EUR": "135.62" },
      "WBTC": { "EUR": "53407.6" },
      "THETA": { "EUR": "5.12" },
      "ICP": { "EUR": "38.26" }
    },
    "sell": {
      "BTC": { "EUR": "53406.8" },
      "LTC": { "EUR": "162.45" },
      "ETH": { "EUR": "3265.01" },
      "BCH": { "EUR": "531.06" },
      "NANO": { "EUR": "4.53" },
      "TRX": { "EUR": "0.0846" },
      "DAI": { "EUR": "0.8575" },
      "DOGE": { "EUR": "0.212" },
      "AVA": { "EUR": "2.67" },
      "BTCV": { "EUR": "6.52" }
    }
  }
}
